<environment>
    <parameter>
        <key>Browser</key>
        <value>Chrome</value>
    </parameter>
    <parameter>
        <key>Browser.Version</key>
        <value>81.0.4044.92</value>
    </parameter>
    <parameter>
        <key>Stand</key>
        <value>Production</value>
    </parameter>
        <parameter>
        <key>ApiUrl</key>
        <value>http://jxair.minhopeonline.com/</value>
    </parameter>
        <parameter>
        <key>python.Version</key>
        <value>3.10.0</value>
    </parameter>
</environment>